abcard/__init__.py
abcard/frame.py
abcard/merge.py
abcard/plot.py
abcard/report.py
abcard/stats.py
abcard/utils.py
abcard/libs/split.dll
abcard/libs/split.dylib
abcard/libs/split.so
abcard-0.1.4.dist-info/licenses/LICENSE
abcard-0.1.4.dist-info/METADATA
abcard-0.1.4.dist-info/WHEEL
abcard-0.1.4.dist-info/top_level.txt
abcard-0.1.4.dist-info/RECORD
