Metadata-Version: 2.4
Name: abcard
Version: 0.1.4
Summary: Primarily used for developing binary classification models and generating reports for production work. 
Author-email: Jack Huang <2422991212@qq.com>
Classifier: Programming Language :: Python :: 3
Classifier: License :: OSI Approved :: GNU Affero General Public License v3
Classifier: Operating System :: OS Independent
Classifier: Operating System :: Microsoft :: Windows
Classifier: Operating System :: POSIX :: Linux
Classifier: Operating System :: MacOS
Requires-Python: >=3.9
License-File: LICENSE
Requires-Dist: numpy>=1.25.2
Requires-Dist: pandas>=1.3.4
Requires-Dist: statsmodels>=0.14.0
Requires-Dist: tqdm>=4.66.1
Requires-Dist: scikit-learn>=1.6.0
Requires-Dist: matplotlib>=3.7.2
Requires-Dist: PyMuPDF>=1.25.2
Requires-Dist: lightgbm>=3.3.1
Dynamic: license-file
